{
    "status": "ok",
    "totalResults": 92,
    "articles": [
        {
            "source": {
                "id": null,
                "name": "Yahoo Entertainment"
            },
            "author": null,
            "title": "Analyst Report: DocuSign Inc",
            "description": null,
            "url": "https://consent.yahoo.com/v2/collectConsent?sessionId=1_cc-session_d58e142b-6730-41a2-ac13-8f0df4c8b870",
            "urlToImage": null,
            "publishedAt": "2024-06-11T11:00:02Z",
            "content": "If you click 'Accept all', we and our partners, including 238 who are part of the IAB Transparency &amp; Consent Framework, will also store and/or access information on a device (in other words, use \u2026 [+678 chars]"
        },
        {
            "source": {
                "id": null,
                "name": "Yahoo Entertainment"
            },
            "author": null,
            "title": "Why DocuSign Stock Dropped Today",
            "description": null,
            "url": "https://consent.yahoo.com/v2/collectConsent?sessionId=1_cc-session_263ea964-e555-4860-9bf9-3c42f9d53908",
            "urlToImage": null,
            "publishedAt": "2024-06-07T15:33:32Z",
            "content": "If you click 'Accept all', we and our partners, including 238 who are part of the IAB Transparency &amp; Consent Framework, will also store and/or access information on a device (in other words, use \u2026 [+678 chars]"
        },
        {
            "source": {
                "id": null,
                "name": "Yahoo Entertainment"
            },
            "author": null,
            "title": "Why DocuSign (DOCU) Shares Are Sliding Today",
            "description": null,
            "url": "https://consent.yahoo.com/v2/collectConsent?sessionId=1_cc-session_b05f1f19-dcb6-49f2-b2e5-085637e13898",
            "urlToImage": null,
            "publishedAt": "2024-06-07T15:32:21Z",
            "content": "If you click 'Accept all', we and our partners, including 238 who are part of the IAB Transparency &amp; Consent Framework, will also store and/or access information on a device (in other words, use \u2026 [+678 chars]"
        },
        {
            "source": {
                "id": null,
                "name": "Yahoo Entertainment"
            },
            "author": null,
            "title": "DocuSign Investors Just Got Some Bullish News",
            "description": null,
            "url": "https://consent.yahoo.com/v2/collectConsent?sessionId=1_cc-session_7eaa5514-b410-4198-bac4-f953dc568e26",
            "urlToImage": null,
            "publishedAt": "2024-06-07T12:51:00Z",
            "content": "If you click 'Accept all', we and our partners, including 238 who are part of the IAB Transparency &amp; Consent Framework, will also store and/or access information on a device (in other words, use \u2026 [+678 chars]"
        },
        {
            "source": {
                "id": null,
                "name": "Yahoo Entertainment"
            },
            "author": null,
            "title": "Should You Buy DocuSign Stock Right Now?",
            "description": null,
            "url": "https://consent.yahoo.com/v2/collectConsent?sessionId=1_cc-session_37459aee-4536-490a-a3f4-642f74d80622",
            "urlToImage": null,
            "publishedAt": "2024-06-10T15:00:00Z",
            "content": "If you click 'Accept all', we and our partners, including 238 who are part of the IAB Transparency &amp; Consent Framework, will also store and/or access information on a device (in other words, use \u2026 [+678 chars]"
        },
        {
            "source": {
                "id": null,
                "name": "Yahoo Entertainment"
            },
            "author": null,
            "title": "DocuSign First Quarter 2025 Earnings: EPS Beats Expectations",
            "description": null,
            "url": "https://consent.yahoo.com/v2/collectConsent?sessionId=1_cc-session_49cff191-3b63-4f71-b112-050385dacfda",
            "urlToImage": null,
            "publishedAt": "2024-06-08T13:18:29Z",
            "content": "If you click 'Accept all', we and our partners, including 238 who are part of the IAB Transparency &amp; Consent Framework, will also store and/or access information on a device (in other words, use \u2026 [+678 chars]"
        },
        {
            "source": {
                "id": null,
                "name": "Yahoo Entertainment"
            },
            "author": null,
            "title": "DocuSign Shares Sink on Guidance. Time to Buy the Dip?",
            "description": null,
            "url": "https://consent.yahoo.com/v2/collectConsent?sessionId=1_cc-session_495b4a5e-6722-4d4a-a34d-54265c0222ce",
            "urlToImage": null,
            "publishedAt": "2024-06-09T18:05:00Z",
            "content": "If you click 'Accept all', we and our partners, including 238 who are part of the IAB Transparency &amp; Consent Framework, will also store and/or access information on a device (in other words, use \u2026 [+678 chars]"
        },
        {
            "source": {
                "id": null,
                "name": "Yahoo Entertainment"
            },
            "author": "GuruFocus Research",
            "title": "Decoding DocuSign Inc (DOCU): A Strategic SWOT Insight",
            "description": "Unveiling the Strengths and Challenges: A Deep Dive into DocuSign Inc (DOCU) SWOT Analysis",
            "url": "https://finance.yahoo.com/news/decoding-docusign-inc-docu-strategic-050334002.html",
            "urlToImage": "https://s.yimg.com/ny/api/res/1.2/4v1UZTcF3hax0W.VF67MUg--/YXBwaWQ9aGlnaGxhbmRlcjt3PTEyMDA7aD03NTc-/https://media.zenfs.com/en/us.finance.gurufocus/73af5860ab24f9df35e0d063c9c4474e",
            "publishedAt": "2024-06-08T05:03:34Z",
            "content": "<ul><li>DocuSign Inc (NASDAQ:DOCU) showcases robust subscription revenue growth and a significant increase in net income.\r\n</li><li>Strategic investments and a growing customer base position DOCU for\u2026 [+6858 chars]"
        },
        {
            "source": {
                "id": null,
                "name": "Yahoo Entertainment"
            },
            "author": null,
            "title": "DocuSign, Inc. (NASDAQ:DOCU) Shares Could Be 35% Below Their Intrinsic Value Estimate",
            "description": null,
            "url": "https://consent.yahoo.com/v2/collectConsent?sessionId=1_cc-session_c6836933-3fc5-4e53-af0b-7e6a85d41285",
            "urlToImage": null,
            "publishedAt": "2024-05-23T14:13:44Z",
            "content": "If you click 'Accept all', we and our partners, including 238 who are part of the IAB Transparency &amp; Consent Framework, will also store and/or access information on a device (in other words, use \u2026 [+678 chars]"
        },
        {
            "source": {
                "id": null,
                "name": "Yahoo Entertainment"
            },
            "author": "GuruFocus Research",
            "title": "Insider Sale: Chief Legal Officer James Shaughnessy Sells Shares of DocuSign Inc (DOCU)",
            "description": "Chief Legal Officer James Shaughnessy of DocuSign Inc (NASDAQ:DOCU) sold 3,600 shares of the company on June 12, 2024, according to a recent SEC Filing.",
            "url": "https://finance.yahoo.com/news/insider-sale-chief-legal-officer-064720618.html",
            "urlToImage": "https://s.yimg.com/ny/api/res/1.2/k1GlkwjTPL9VWUR.ekaoxQ--/YXBwaWQ9aGlnaGxhbmRlcjt3PTEyMDA7aD01MjU-/https://media.zenfs.com/en/us.finance.gurufocus/8f4f8cd2b24019b611245b35579e4eac",
            "publishedAt": "2024-06-13T06:47:20Z",
            "content": "Chief Legal Officer James Shaughnessy of DocuSign Inc (NASDAQ:DOCU) sold 3,600 shares of the company on June 12, 2024, according to a recent SEC Filing. Following this transaction, the insider now ow\u2026 [+2410 chars]"
        },
        {
            "source": {
                "id": null,
                "name": "Yahoo Entertainment"
            },
            "author": "GuruFocus Research",
            "title": "Insider Selling: DocuSign Inc (DOCU) President and CEO Allan Thygesen Sells 7,576 Shares",
            "description": "On June 3, 2024, Allan Thygesen, President and CEO of DocuSign Inc (NASDAQ:DOCU), sold 7,576 shares of the company.",
            "url": "https://finance.yahoo.com/news/insider-selling-docusign-inc-docu-230222004.html",
            "urlToImage": "https://s.yimg.com/ny/api/res/1.2/LHOUJkloUttkmlE1dDXubg--/YXBwaWQ9aGlnaGxhbmRlcjt3PTEyMDA7aD01MjU-/https://media.zenfs.com/en/us.finance.gurufocus/a0af4b0b094a5d0529b8df586a59532e",
            "publishedAt": "2024-06-04T23:02:22Z",
            "content": "On June 3, 2024, Allan Thygesen, President and CEO of DocuSign Inc (NASDAQ:DOCU), sold 7,576 shares of the company. The transaction was reported in a recent SEC Filing. Following this sale, the insid\u2026 [+2321 chars]"
        },
        {
            "source": {
                "id": null,
                "name": "CNBC"
            },
            "author": null,
            "title": "DocuSign chief says company wants to stay public after reports of private equity takeover interest",
            "description": "DocuSign CEO Allan Thygesen said the online contract-signing platform is committed to staying public after rumored takeover interest from private equity firms.",
            "url": "https://www.cnbc.com/2024/05/22/docusign-ceo-says-wants-to-stay-public-after-pe-takeover-speculation.html",
            "urlToImage": null,
            "publishedAt": "2024-05-22T07:51:00Z",
            "content": "The DocuSign website is seen on a laptop in Dobbs Ferry, New York, April 1, 2021.\r\nContract management platform DocuSign is committed to remaining a public company and is working to convince investor\u2026 [+3887 chars]"
        },
        {
            "source": {
                "id": "newsweek",
                "name": "Newsweek"
            },
            "author": "Lauren Giella",
            "title": "Docusign Delivers Trust, Security While Maintaining 'Ease of Use,' CEO Says",
            "description": "Over the past 20 years, Docusign has continued to modernize the agreement space while maintaining customer trust.",
            "url": "https://www.newsweek.com/docusign-delivers-trust-security-while-maintaining-ease-use-ceo-says-1910525",
            "urlToImage": "https://d.newsweek.com/en/full/2407183/docusign-iam.png",
            "publishedAt": "2024-06-12T13:45:01Z",
            "content": "Trust is the foundation of any agreement\u2014the parties involved must all be satisfied with the terms and conditions, believe everyone is acting in good faith and feel that any sensitive personal inform\u2026 [+10774 chars]"
        },
        {
            "source": {
                "id": "fortune",
                "name": "Fortune"
            },
            "author": "Eleanor Pringle",
            "title": "Docusign CEO says while it\u2019s true Americans work harder than Europeans, maybe Americans aren\u2019t happier",
            "description": "Allan Thygesen says \"these are conscious choices that societies have made about the trade-off between work and leisure time.\"",
            "url": "https://fortune.com/2024/06/08/allan-thygesen-docusign-ceo-return-to-work-flexibility/",
            "urlToImage": "https://fortune.com/img-assets/wp-content/uploads/2024/06/Copy-of-FeatTemplate-46.jpg?resize=1200,600",
            "publishedAt": "2024-06-08T09:00:00Z",
            "content": "In a tech hub like San Francisco, its increasingly rare to find a job that will still let you work from home the majority of the week. But at $12 billion company Docusign, thats still the casein fact\u2026 [+6775 chars]"
        },
        {
            "source": {
                "id": null,
                "name": "Investopedia"
            },
            "author": "Bill McColl",
            "title": "Top Stock Movers Now: GameStop, Docusign, Vail Resorts, and More",
            "description": "U.S. equities gained at midday Friday, June 7, 2024, rebounding from earlier losses following a stronger-than-expected jobs report that dampened hopes of interest rate cuts by the Federal Reserve.",
            "url": "https://www.investopedia.com/top-stock-movers-now-gamestop-docusign-vail-resorts-and-more-8660134",
            "urlToImage": "https://www.investopedia.com/thmb/O1sG8qHSdZyMIGt9cnA0iPtzZ1g=/1500x0/filters:no_upscale():max_bytes(150000):strip_icc()/GettyImages-2155799578-2bf179fce63048edb50aa369ffbea94f.jpg",
            "publishedAt": "2024-06-07T17:33:55Z",
            "content": "<ul><li>U.S. equities gained at midday Friday, June 7, 2024, rebounding from earlier losses following a stronger-than-expected jobs report that dampened hopes of interest rate cuts by the Federal Res\u2026 [+2280 chars]"
        },
        {
            "source": {
                "id": null,
                "name": "pymnts.com"
            },
            "author": "PYMNTS",
            "title": "DocuSign CEO Says Company Will Remain Public",
            "description": "DocuSign\u00a0will stay a public company, according to the electronic signature platform\u2019s CEO. Allan Thygesen\u00a0made that pronouncement in an\u00a0interview\u00a0with CNBC published Wednesday (May 23), following reports that private equity firms had considered a takeover. \u201cW\u2026",
            "url": "https://www.pymnts.com/business/2024/docusign-ceo-says-company-will-remain-public/",
            "urlToImage": "https://www.pymnts.com/wp-content/uploads/2023/12/DocuSign.jpg",
            "publishedAt": "2024-05-22T16:09:52Z",
            "content": "DocuSign\u00a0will stay a public company, according to the electronic signature platforms CEO.\r\nAllan Thygesen\u00a0made that pronouncement in an\u00a0interview\u00a0with CNBC published Wednesday (May 23), following rep\u2026 [+2533 chars]"
        },
        {
            "source": {
                "id": null,
                "name": "Marketscreener.com"
            },
            "author": null,
            "title": "DocuSign : First Quarter 2025 Earnings Slides",
            "description": "(marketscreener.com) \n \n Smarter, Easier,\n \n \n Trusted Agreements\n \n \n Q1 FY25\n \n \n \n \n \n \n Safe Harbor\n \n \n This presentation contains \"forward-looking\" statements within the meaning of Section 27A of the Securities Act of 1933, as amended,...https://www.mar\u2026",
            "url": "https://www.marketscreener.com/quote/stock/DOCUSIGN-INC-43180302/news/DocuSign-First-Quarter-2025-Earnings-Slides-46923139/",
            "urlToImage": "https://www.marketscreener.com/images/twitter_MS_fdblanc.png",
            "publishedAt": "2024-06-06T20:08:13Z",
            "content": "Safe Harbor\r\nThis presentation contains \"forward-looking\" statements within the meaning of Section 27A of the Securities Act of 1933, as amended, and Section 21E of the Securities Exchange Act of 193\u2026 [+5499 chars]"
        },
        {
            "source": {
                "id": null,
                "name": "Biztoc.com"
            },
            "author": "pymnts.com",
            "title": "DocuSign CEO Says Company Will Remain Public",
            "description": "DocuSign will stay a public company, according to the electronic signature platform\u2019s CEO. Allan Thygesen made that pronouncement in an interview with CNBC published Wednesday (May 23), following reports that private equity firms had considered a takeover. \u201cW\u2026",
            "url": "https://biztoc.com/x/740a58016e04cef4",
            "urlToImage": "https://c.biztoc.com/p/740a58016e04cef4/s.webp",
            "publishedAt": "2024-05-22T16:14:10Z",
            "content": "DocuSign will stay a public company, according to the electronic signature platforms CEO.Allan Thygesen made that pronouncement in an interview with CNBC published Wednesday (May 23), following repor\u2026 [+300 chars]"
        },
        {
            "source": {
                "id": null,
                "name": "Marketscreener.com"
            },
            "author": null,
            "title": "DocuSign : First Quarter 2025 Press Release",
            "description": "(marketscreener.com) \n \n \n DOCUSIGN, INC.\n \n \n Exhibit 99.1\n \n \n Docusign Announces First Quarter Fiscal 2025 Financial Results;\n \n \n Announces $1.0 Billion Increase to Share Repurchase Program\n \n \n San Francisco - June 6, 2024 - Docusign, Inc. today...https:\u2026",
            "url": "https://www.marketscreener.com/quote/stock/DOCUSIGN-INC-43180302/news/DocuSign-First-Quarter-2025-Press-Release-46923140/",
            "urlToImage": "https://www.marketscreener.com/images/twitter_MS_fdnoir.png",
            "publishedAt": "2024-06-06T20:08:13Z",
            "content": "DOCUSIGN, INC.\r\nForward-Looking Statements\r\nThis press release contains \"forward-looking\" statements within the meaning of Section 27A of the Securities Act of 1933, as amended, and Section 21E of th\u2026 [+6514 chars]"
        },
        {
            "source": {
                "id": null,
                "name": "Biztoc.com"
            },
            "author": "fool.com",
            "title": "DocuSign Investors Just Got Some Bullish News",
            "description": "Prospective investors can sign on the dotted line as DocuSign finalizes an AI-focused acquisition. DocuSign (DOCU -4.87%) was a darling of the market during and in the year following the onset of COVID. But with the pandemic catalyst fading in the rearview mi\u2026",
            "url": "https://biztoc.com/x/5d62b6a13665813e",
            "urlToImage": "https://c.biztoc.com/p/5d62b6a13665813e/og.webp",
            "publishedAt": "2024-06-07T16:14:05Z",
            "content": "Prospective investors can sign on the dotted line as DocuSign finalizes an AI-focused acquisition.DocuSign (DOCU -4.87%) was a darling of the market during and in the year following the onset of COVI\u2026 [+292 chars]"
        },
        {
            "source": {
                "id": null,
                "name": "ETF Daily News"
            },
            "author": "MarketBeat News",
            "title": "DocuSign (NASDAQ:DOCU) PT Lowered to $60.00",
            "description": "DocuSign (NASDAQ:DOCU \u2013 Get Free Report) had its price target lowered by analysts at Piper Sandler from $65.00 to $60.00 in a research note issued to investors on Friday, Benzinga reports. The brokerage presently has a \u201cneutral\u201d rating on the stock. Piper San\u2026",
            "url": "https://www.etfdailynews.com/2024/06/09/docusign-nasdaqdocu-pt-lowered-to-60-00/",
            "urlToImage": "https://www.americanbankingnews.com/wp-content/timthumb/timthumb.php?src=https://www.marketbeat.com/logos/docusign-inc-logo-1200x675.jpg?v=20240109092218&w=240&h=240&zc=2",
            "publishedAt": "2024-06-09T07:56:45Z",
            "content": "DocuSign (NASDAQ:DOCU \u2013 Get Free Report) had its price target lowered by analysts at Piper Sandler from $65.00 to $60.00 in a research note issued to investors on Friday, Benzinga reports. The broker\u2026 [+5694 chars]"
        },
        {
            "source": {
                "id": null,
                "name": "ETF Daily News"
            },
            "author": "MarketBeat News",
            "title": "DocuSign, Inc. (NASDAQ:DOCU) Short Interest Update",
            "description": "DocuSign, Inc. (NASDAQ:DOCU \u2013 Get Free Report) saw a large increase in short interest in the month of May. As of May 15th, there was short interest totalling 8,630,000 shares, an increase of 12.1% from the April 30th total of 7,700,000 shares. Based on an ave\u2026",
            "url": "https://www.etfdailynews.com/2024/06/03/docusign-inc-nasdaqdocu-short-interest-update/",
            "urlToImage": "https://www.americanbankingnews.com/wp-content/timthumb/timthumb.php?src=https://www.marketbeat.com/logos/docusign-inc-logo-1200x675.jpg?v=20240109092218&w=240&h=240&zc=2",
            "publishedAt": "2024-06-03T06:32:44Z",
            "content": "DocuSign, Inc. (NASDAQ:DOCU \u2013 Get Free Report) saw a large increase in short interest in the month of May. As of May 15th, there was short interest totalling 8,630,000 shares, an increase of 12.1% fr\u2026 [+5998 chars]"
        },
        {
            "source": {
                "id": null,
                "name": "ETF Daily News"
            },
            "author": "MarketBeat News",
            "title": "DocuSign (NASDAQ:DOCU) PT Lowered to $62.00",
            "description": "DocuSign (NASDAQ:DOCU \u2013 Get Free Report) had its target price decreased by stock analysts at Morgan Stanley from $65.00 to $62.00 in a research note issued to investors on Friday, Benzinga reports. The firm currently has an \u201cequal weight\u201d rating on the stock.\u2026",
            "url": "https://www.etfdailynews.com/2024/06/09/docusign-nasdaqdocu-pt-lowered-to-62-00/",
            "urlToImage": "https://www.americanbankingnews.com/wp-content/timthumb/timthumb.php?src=https://www.marketbeat.com/logos/docusign-inc-logo-1200x675.jpg?v=20240109092218&w=240&h=240&zc=2",
            "publishedAt": "2024-06-09T07:10:43Z",
            "content": "DocuSign (NASDAQ:DOCU \u2013 Get Free Report) had its target price decreased by stock analysts at Morgan Stanley from $65.00 to $62.00 in a research note issued to investors on Friday, Benzinga reports. T\u2026 [+5704 chars]"
        },
        {
            "source": {
                "id": null,
                "name": "Marketscreener.com"
            },
            "author": null,
            "title": "DocuSign : First Quarter 2025 Prepared Remarks",
            "description": "(marketscreener.com) \n \n \n Q1 FY25 Investor Prepared Remarks\n \n \n June 6, 2024\n \n \n Allan Thygesen, CEO\n \n \n Blake Grayson, CFO\n \n \n \n \n \n \n \n Docusign Q1'25 Investor Prepared Remarks\n \n ...https://www.marketscreener.com/quote/stock/DOCUSIGN-INC-43180302/news\u2026",
            "url": "https://www.marketscreener.com/quote/stock/DOCUSIGN-INC-43180302/news/DocuSign-First-Quarter-2025-Prepared-Remarks-46923167/",
            "urlToImage": "https://www.marketscreener.com/images/twitter_MS_fdnoir.png",
            "publishedAt": "2024-06-06T20:14:08Z",
            "content": "This presentation contains \"forward-looking\" statements within the meaning of Section 27A of the Securities Act of 1933, as amended, and Section 21E of the Securities Exchange Act of 1934, as amended\u2026 [+10401 chars]"
        },
        {
            "source": {
                "id": null,
                "name": "InvestorsObserver"
            },
            "author": "InvestorsObserver",
            "title": "DOCU (DocuSign) Revenue Breakdown and Strategies",
            "description": "2024-06-08 10:34:22 ET         DocuSign&#x2019;s (DOCU) solid first-quarter earnings topped analysts&#x2019; earnings and revenue estimates in the April quarter. Further, the company&#x2019;s long-term outlook appears promising, driven by its strategic...",
            "url": "https://www.investorsobserver.com/news/qm-news/6685277792842985",
            "urlToImage": "https://s3.amazonaws.com/images.investorsobserver.com/io-logo-800x450.jpg",
            "publishedAt": "2024-06-08T10:34:22Z",
            "content": "News Home\r\n 2024-06-08 10:34:22 ET\r\nDocuSign\u2019s (DOCU) solid first-quarter earnings topped analysts\u2019 earnings and revenue estimates in the April quarter. Further, the company\u2019s long-term outlook appea\u2026 [+9033 chars]"
        },
        {
            "source": {
                "id": null,
                "name": "ETF Daily News"
            },
            "author": "MarketBeat News",
            "title": "Hilltop Holdings Inc. Has $869,000 Holdings in DocuSign, Inc. (NASDAQ:DOCU)",
            "description": "Hilltop Holdings Inc. cut its stake in DocuSign, Inc. (NASDAQ:DOCU \u2013 Free Report) by 26.2% in the fourth quarter, according to the company in its most recent filing with the Securities and Exchange Commission. The firm owned 14,618 shares of the company\u2019s sto\u2026",
            "url": "https://www.etfdailynews.com/2024/05/28/hilltop-holdings-inc-has-869000-holdings-in-docusign-inc-nasdaqdocu/",
            "urlToImage": "https://www.americanbankingnews.com/wp-content/timthumb/timthumb.php?src=https://www.marketbeat.com/logos/docusign-inc-logo-1200x675.jpg?v=20240109092218&w=240&h=240&zc=2",
            "publishedAt": "2024-05-28T14:16:48Z",
            "content": "Hilltop Holdings Inc. cut its stake in DocuSign, Inc. (NASDAQ:DOCU \u2013 Free Report) by 26.2% in the fourth quarter, according to the company in its most recent filing with the Securities and Exchange C\u2026 [+6418 chars]"
        },
        {
            "source": {
                "id": null,
                "name": "ETF Daily News"
            },
            "author": "MarketBeat News",
            "title": "DocuSign (DOCU) Set to Announce Earnings on Thursday",
            "description": "DocuSign (NASDAQ:DOCU \u2013 Get Free Report) is set to post its quarterly earnings results after the market closes on Thursday, June 6th. Analysts expect DocuSign to post earnings of $0.79 per share for the quarter. DocuSign has set its FY 2025 guidance at EPS an\u2026",
            "url": "https://www.etfdailynews.com/2024/05/30/docusign-docu-set-to-announce-earnings-on-thursday/",
            "urlToImage": "https://www.americanbankingnews.com/wp-content/timthumb/timthumb.php?src=https://www.marketbeat.com/logos/docusign-inc-logo-1200x675.jpg?v=20240109092218&w=240&h=240&zc=2",
            "publishedAt": "2024-05-30T05:36:43Z",
            "content": "DocuSign (NASDAQ:DOCU \u2013 Get Free Report) is set to post its quarterly earnings results after the market closes on Thursday, June 6th. Analysts expect DocuSign to post earnings of $0.79 per share for \u2026 [+4605 chars]"
        },
        {
            "source": {
                "id": null,
                "name": "ETF Daily News"
            },
            "author": "MarketBeat News",
            "title": "Parallel Advisors LLC Has $367,000 Stake in DocuSign, Inc. (NASDAQ:DOCU)",
            "description": "Parallel Advisors LLC decreased its holdings in DocuSign, Inc. (NASDAQ:DOCU \u2013 Free Report) by 25.4% in the 4th quarter, according to its most recent filing with the Securities & Exchange Commission. The institutional investor owned 6,171 shares of the company\u2026",
            "url": "https://www.etfdailynews.com/2024/06/02/parallel-advisors-llc-has-367000-stake-in-docusign-inc-nasdaqdocu/",
            "urlToImage": "https://www.americanbankingnews.com/wp-content/timthumb/timthumb.php?src=https://www.marketbeat.com/logos/docusign-inc-logo-1200x675.jpg?v=20240109092218&w=240&h=240&zc=2",
            "publishedAt": "2024-06-02T12:30:46Z",
            "content": "Parallel Advisors LLC decreased its holdings in DocuSign, Inc. (NASDAQ:DOCU \u2013 Free Report) by 25.4% in the 4th quarter, according to its most recent filing with the Securities &amp; Exchange Commissi\u2026 [+6252 chars]"
        },
        {
            "source": {
                "id": null,
                "name": "Marketscreener.com"
            },
            "author": null,
            "title": "Docusign Completes Acquisition of Lexion to Accelerate Intelligent Agreement Management",
            "description": "(marketscreener.com) \n\nSAN FRANCISCO, May 31, 2024 /PRNewswire/ -- Docusign today announced that it has completed the acquisition of Lexion, a leading AI-powered agreement management company. This strengthens Docusign's position in Intelligent Agreement Manag\u2026",
            "url": "https://www.marketscreener.com/quote/stock/DOCUSIGN-INC-43180302/news/Docusign-Completes-Acquisition-of-Lexion-to-Accelerate-Intelligent-Agreement-Management-46877896/",
            "urlToImage": "https://www.marketscreener.com/images/twitter_MS_fdnoir.png",
            "publishedAt": "2024-05-31T20:01:08Z",
            "content": "SAN FRANCISCO, May 31, 2024 /PRNewswire/ -- Docusign (NASDAQ: DOCU) today announced that it has completed the acquisition of Lexion\r\n, a leading AI-powered agreement management company. This strength\u2026 [+3643 chars]"
        },
        {
            "source": {
                "id": null,
                "name": "Biztoc.com"
            },
            "author": "benzinga.com",
            "title": "What's Going On With DocuSign Shares On Friday?",
            "description": "DocuSign, Inc. DOCU shares are trading lower in the premarket session on Friday. BofA Securities analyst Brad Sills maintains DocuSign with a Neutral and lowers the price target from $72 to $60. Also, Baird analyst William Power maintains the Neutral and lowe\u2026",
            "url": "https://biztoc.com/x/67ff469845a765a4",
            "urlToImage": "https://c.biztoc.com/p/67ff469845a765a4/s.webp",
            "publishedAt": "2024-06-07T13:16:08Z",
            "content": "DocuSign, Inc. DOCU shares are trading lower in the premarket session on Friday.BofA Securities analyst Brad Sills maintains DocuSign with a Neutral and lowers the price target from $72 to $60.Also, \u2026 [+302 chars]"
        },
        {
            "source": {
                "id": null,
                "name": "ETF Daily News"
            },
            "author": "MarketBeat News",
            "title": "Brandywine Managers LLC Takes $250,000 Position in DocuSign, Inc. (NASDAQ:DOCU)",
            "description": "Brandywine Managers LLC bought a new stake in DocuSign, Inc. (NASDAQ:DOCU \u2013 Free Report) in the 4th quarter, according to its most recent 13F filing with the SEC. The firm bought 4,211 shares of the company\u2019s stock, valued at approximately $250,000. Other lar\u2026",
            "url": "https://www.etfdailynews.com/2024/06/13/brandywine-managers-llc-takes-250000-position-in-docusign-inc-nasdaqdocu/",
            "urlToImage": "https://www.americanbankingnews.com/wp-content/timthumb/timthumb.php?src=https://www.marketbeat.com/logos/docusign-inc-logo-1200x675.jpg?v=20240109092218&w=240&h=240&zc=2",
            "publishedAt": "2024-06-13T11:54:46Z",
            "content": "Brandywine Managers LLC bought a new stake in DocuSign, Inc. (NASDAQ:DOCU \u2013 Free Report) in the 4th quarter, according to its most recent 13F filing with the SEC. The firm bought 4,211 shares of the \u2026 [+5255 chars]"
        },
        {
            "source": {
                "id": null,
                "name": "Investing.com"
            },
            "author": "Investing.com",
            "title": "Docusign reported a 7% year-over-year increase in revenues",
            "description": "Docusign reported a 7% year-over-year increase in revenues",
            "url": "https://www.investing.com/news/company-news/docusign-reported-a-7-yearoveryear-increase-in-revenues-93CH-3474476",
            "urlToImage": "https://i-invdn-com.investing.com/news/news_pile_69x52._800x533_L_1419494209.jpg",
            "publishedAt": "2024-06-06T20:10:45Z",
            "content": "SAN FRANCISCO - Docusign Inc. (NASDAQ: DOCU), the electronic agreement service provider, disclosed its fiscal results for the first quarter ending April 30, 2024, today, revealing a 7% year-over-year\u2026 [+3610 chars]"
        },
        {
            "source": {
                "id": null,
                "name": "ETF Daily News"
            },
            "author": "MarketBeat News",
            "title": "DocuSign (NASDAQ:DOCU) Earns Hold Rating from Needham & Company LLC",
            "description": "DocuSign (NASDAQ:DOCU \u2013 Get Free Report)\u2018s stock had its \u201chold\u201d rating reaffirmed by Needham & Company LLC in a research report issued to clients and investors on Friday, Benzinga reports. A number of other equities analysts have also commented on the stock. \u2026",
            "url": "https://www.etfdailynews.com/2024/06/07/docusign-nasdaqdocu-earns-hold-rating-from-needham-company-llc/",
            "urlToImage": "https://www.americanbankingnews.com/wp-content/timthumb/timthumb.php?src=https://www.marketbeat.com/logos/docusign-inc-logo-1200x675.jpg?v=20240109092218&w=240&h=240&zc=2",
            "publishedAt": "2024-06-07T13:28:44Z",
            "content": "DocuSign (NASDAQ:DOCU \u2013 Get Free Report)\u2018s stock had its \u201chold\u201d rating reaffirmed by Needham &amp; Company LLC in a research report issued to clients and investors on Friday, Benzinga reports.\r\nA num\u2026 [+5936 chars]"
        },
        {
            "source": {
                "id": null,
                "name": "ETF Daily News"
            },
            "author": "MarketBeat News",
            "title": "Intech Investment Management LLC Increases Holdings in DocuSign, Inc. (NASDAQ:DOCU)",
            "description": "Intech Investment Management LLC boosted its position in DocuSign, Inc. (NASDAQ:DOCU \u2013 Free Report) by 32.6% in the 4th quarter, according to its most recent filing with the Securities and Exchange Commission (SEC). The institutional investor owned 32,451 sha\u2026",
            "url": "https://www.etfdailynews.com/2024/05/28/intech-investment-management-llc-increases-holdings-in-docusign-inc-nasdaqdocu/",
            "urlToImage": "https://www.americanbankingnews.com/wp-content/timthumb/timthumb.php?src=https://www.marketbeat.com/logos/docusign-inc-logo-1200x675.jpg?v=20240109092218&w=240&h=240&zc=2",
            "publishedAt": "2024-05-28T13:26:45Z",
            "content": "Intech Investment Management LLC boosted its position in DocuSign, Inc. (NASDAQ:DOCU \u2013 Free Report) by 32.6% in the 4th quarter, according to its most recent filing with the Securities and Exchange C\u2026 [+6179 chars]"
        },
        {
            "source": {
                "id": null,
                "name": "ETF Daily News"
            },
            "author": "MarketBeat News",
            "title": "DocuSign (NASDAQ:DOCU) Shares Gap Down Following Analyst Downgrade",
            "description": "DocuSign, Inc. (NASDAQ:DOCU \u2013 Get Free Report)\u2019s stock price gapped down prior to trading on Friday after Morgan Stanley lowered their price target on the stock from $65.00 to $62.00. The stock had previously closed at $54.60, but opened at $51.38. Morgan Sta\u2026",
            "url": "https://www.etfdailynews.com/2024/06/08/docusign-nasdaqdocu-shares-gap-down-following-analyst-downgrade/",
            "urlToImage": "https://www.americanbankingnews.com/wp-content/timthumb/timthumb.php?src=https://www.marketbeat.com/logos/docusign-inc-logo-1200x675.jpg?v=20240109092218&w=240&h=240&zc=2",
            "publishedAt": "2024-06-08T05:30:43Z",
            "content": "DocuSign, Inc. (NASDAQ:DOCU \u2013 Get Free Report)\u2019s stock price gapped down prior to trading on Friday after Morgan Stanley lowered their price target on the stock from $65.00 to $62.00. The stock had p\u2026 [+5401 chars]"
        },
        {
            "source": {
                "id": null,
                "name": "ETF Daily News"
            },
            "author": "MarketBeat News",
            "title": "CIBC Asset Management Inc Lowers Holdings in DocuSign, Inc. (NASDAQ:DOCU)",
            "description": "CIBC Asset Management Inc lessened its stake in DocuSign, Inc. (NASDAQ:DOCU \u2013 Free Report) by 6.7% in the 4th quarter, according to the company in its most recent 13F filing with the Securities and Exchange Commission (SEC). The fund owned 6,527 shares of the\u2026",
            "url": "https://www.etfdailynews.com/2024/06/11/cibc-asset-management-inc-lowers-holdings-in-docusign-inc-nasdaqdocu/",
            "urlToImage": "https://www.americanbankingnews.com/wp-content/timthumb/timthumb.php?src=https://www.marketbeat.com/logos/docusign-inc-logo-1200x675.jpg?v=20240109092218&w=240&h=240&zc=2",
            "publishedAt": "2024-06-11T08:48:41Z",
            "content": "CIBC Asset Management Inc lessened its stake in DocuSign, Inc. (NASDAQ:DOCU \u2013 Free Report) by 6.7% in the 4th quarter, according to the company in its most recent 13F filing with the Securities and E\u2026 [+5145 chars]"
        },
        {
            "source": {
                "id": null,
                "name": "ETF Daily News"
            },
            "author": "MarketBeat News",
            "title": "DocuSign, Inc. (NASDAQ:DOCU) Director Sells $27,405.08 in Stock",
            "description": "DocuSign, Inc. (NASDAQ:DOCU \u2013 Get Free Report) Director Teresa Briggs sold 499 shares of the firm\u2019s stock in a transaction on Friday, May 31st. The shares were sold at an average price of $54.92, for a total value of $27,405.08. Following the completion of th\u2026",
            "url": "https://www.etfdailynews.com/2024/06/03/docusign-inc-nasdaqdocu-director-sells-27405-08-in-stock/",
            "urlToImage": "https://www.americanbankingnews.com/wp-content/timthumb/timthumb.php?src=https://www.marketbeat.com/logos/docusign-inc-logo-1200x675.jpg?v=20240109092218&w=240&h=240&zc=2",
            "publishedAt": "2024-06-03T10:52:41Z",
            "content": "DocuSign, Inc. (NASDAQ:DOCU \u2013 Get Free Report) Director Teresa Briggs sold 499 shares of the firm\u2019s stock in a transaction on Friday, May 31st. The shares were sold at an average price of $54.92, for\u2026 [+4338 chars]"
        },
        {
            "source": {
                "id": null,
                "name": "ETF Daily News"
            },
            "author": "MarketBeat News",
            "title": "Brokerages Set DocuSign, Inc. (NASDAQ:DOCU) PT at $60.25",
            "description": "DocuSign, Inc. (NASDAQ:DOCU \u2013 Get Free Report) has received an average rating of \u201cHold\u201d from the eleven ratings firms that are presently covering the firm, Marketbeat Ratings reports. Two research analysts have rated the stock with a sell recommendation, seve\u2026",
            "url": "https://www.etfdailynews.com/2024/06/02/brokerages-set-docusign-inc-nasdaqdocu-pt-at-60-25/",
            "urlToImage": "https://www.americanbankingnews.com/wp-content/timthumb/timthumb.php?src=https://www.marketbeat.com/logos/docusign-inc-logo-1200x675.jpg?v=20240109092218&w=240&h=240&zc=2",
            "publishedAt": "2024-06-02T06:24:47Z",
            "content": "DocuSign, Inc. (NASDAQ:DOCU \u2013 Get Free Report) has received an average rating of \u201cHold\u201d from the eleven ratings firms that are presently covering the firm, Marketbeat Ratings reports. Two research an\u2026 [+5222 chars]"
        },
        {
            "source": {
                "id": null,
                "name": "Biztoc.com"
            },
            "author": "tipranks.com",
            "title": "DOCU Earnings: DocuSign Sinks despite Solid Q1 Results",
            "description": "Shares of DocuSign (NASDAQ:DOCU) sank in after-hours trading after the electronic signature company reported earnings for its first quarter of Fisc... #docusign #fisc",
            "url": "https://biztoc.com/x/3fae2a39d8f81edd",
            "urlToImage": "https://c.biztoc.com/p/3fae2a39d8f81edd/s.webp",
            "publishedAt": "2024-06-06T20:38:12Z",
            "content": "Shares of DocuSign (NASDAQ:DOCU) sank in after-hours trading after the electronic signature company reported earnings for its first quarter of Fisc...\r\n#docusign#fisc\r\nThis story appeared on tipranks\u2026 [+6 chars]"
        },
        {
            "source": {
                "id": null,
                "name": "Marketscreener.com"
            },
            "author": "Romain Fournier",
            "title": "Stocks in motion: Docusign and Samsara fall sharply",
            "description": "(marketscreener.com) Why is it up? Why is it down? Here's a few comments on the unusual variations affecting stocks on the NYSE today. Only when they are reliable and documented: we avoid nonsense whenever possible! https://www.marketscreener.com/news/latest/\u2026",
            "url": "https://www.marketscreener.com/news/latest/Stocks-in-motion-Docusign-and-Samsara-fall-sharply-46930071/",
            "urlToImage": "https://www.zonebourse.com/images/ImagesTagged/zbimg_2981691_800.png",
            "publishedAt": "2024-06-07T14:21:40Z",
            "content": "Why is it up? Why is it down? Here's a few comments on the unusual variations affecting stocks on the NYSE today. Only when they are reliable and documented: we avoid nonsense whenever possible! \r\n U\u2026 [+1993 chars]"
        },
        {
            "source": {
                "id": null,
                "name": "Investing.com"
            },
            "author": "Investing.com",
            "title": "Baird cuts Docusign shares target on modest earnings results",
            "description": "Baird cuts Docusign shares target on modest earnings results",
            "url": "https://www.investing.com/news/company-news/baird-cuts-docusign-shares-target-on-modest-earnings-results-93CH-3475523",
            "urlToImage": "https://i-invdn-com.investing.com/news/World_News_10_800x533_L_1420026292.jpg",
            "publishedAt": "2024-06-07T11:51:43Z",
            "content": "On Friday, Baird adjusted its outlook on Docusign Inc. (NASDAQ: DOCU) shares, reducing the price target to $55 from the previous $65 while maintaining a Neutral rating on the stock. \r\nThe revision fo\u2026 [+3976 chars]"
        },
        {
            "source": {
                "id": null,
                "name": "ETF Daily News"
            },
            "author": "MarketBeat News",
            "title": "Jones Financial Companies Lllp Takes Position in DocuSign, Inc. (NASDAQ:DOCU)",
            "description": "Jones Financial Companies Lllp acquired a new position in DocuSign, Inc. (NASDAQ:DOCU \u2013 Free Report) during the fourth quarter, according to the company in its most recent filing with the Securities & Exchange Commission. The firm acquired 987 shares of the c\u2026",
            "url": "https://www.etfdailynews.com/2024/06/07/jones-financial-companies-lllp-takes-position-in-docusign-inc-nasdaqdocu/",
            "urlToImage": "https://www.americanbankingnews.com/wp-content/timthumb/timthumb.php?src=https://www.marketbeat.com/logos/docusign-inc-logo-1200x675.jpg?v=20240109092218&w=240&h=240&zc=2",
            "publishedAt": "2024-06-07T14:06:42Z",
            "content": "Jones Financial Companies Lllp acquired a new position in DocuSign, Inc. (NASDAQ:DOCU \u2013 Free Report) during the fourth quarter, according to the company in its most recent filing with the Securities \u2026 [+5904 chars]"
        },
        {
            "source": {
                "id": null,
                "name": "ETF Daily News"
            },
            "author": "MarketBeat News",
            "title": "Oppenheimer & Co. Inc. Cuts Stock Position in DocuSign, Inc. (NASDAQ:DOCU)",
            "description": "Oppenheimer & Co. Inc. lessened its stake in DocuSign, Inc. (NASDAQ:DOCU \u2013 Free Report) by 5.4% in the fourth quarter, HoldingsChannel reports. The fund owned 27,854 shares of the company\u2019s stock after selling 1,592 shares during the period. Oppenheimer & Co.\u2026",
            "url": "https://www.etfdailynews.com/2024/06/10/oppenheimer-co-inc-cuts-stock-position-in-docusign-inc-nasdaqdocu/",
            "urlToImage": "https://www.americanbankingnews.com/wp-content/timthumb/timthumb.php?src=https://www.marketbeat.com/logos/docusign-inc-logo-1200x675.jpg?v=20240109092218&w=240&h=240&zc=2",
            "publishedAt": "2024-06-10T09:56:42Z",
            "content": "Oppenheimer &amp; Co. Inc. lessened its stake in DocuSign, Inc. (NASDAQ:DOCU \u2013 Free Report) by 5.4% in the fourth quarter, HoldingsChannel reports. The fund owned 27,854 shares of the company\u2019s stock\u2026 [+5949 chars]"
        },
        {
            "source": {
                "id": null,
                "name": "Investing.com"
            },
            "author": "Investing.com",
            "title": "Docusign shares maintain Market Outperform amid steady pricing, repurchase plan",
            "description": "Docusign shares maintain Market Outperform amid steady pricing, repurchase plan",
            "url": "https://www.investing.com/news/company-news/docusign-shares-maintain-market-outperform-amid-steady-pricing-repurchase-plan-93CH-3480035",
            "urlToImage": "https://i-invdn-com.investing.com/news/news_six_pile_69x52._800x533_L_1419494215.jpg",
            "publishedAt": "2024-06-11T19:14:39Z",
            "content": "On Tuesday, JMP Securities maintained a bullish stance on Docusign Inc. (NASDAQ: DOCU), keeping a Market Outperform rating and an $84.00 stock price target. The firm's outlook remains positive despit\u2026 [+2843 chars]"
        },
        {
            "source": {
                "id": null,
                "name": "Investing.com"
            },
            "author": "Investing.com",
            "title": "HealthLynked Introduces Innovative Online Medical Record Request Form Using DocuSign",
            "description": "HealthLynked Introduces Innovative Online Medical Record Request Form Using DocuSign",
            "url": "https://www.investing.com/news/press-releases/healthlynked-introduces-innovative-online-medical-record-request-form-using-docusign-93CH-3481586",
            "urlToImage": "https://i-invdn-com.investing.com/news/news_pile_69x52._800x533_L_1419494209.jpg",
            "publishedAt": "2024-06-12T15:24:05Z",
            "content": "NAPLES, Fla., June 12, 2024 (GLOBE NEWSWIRE) -- via IBN HealthLynked Corp. (OTCQB: HLYK), a leading provider of healthcare technology solutions, announces its new online medical record request form, \u2026 [+7470 chars]"
        },
        {
            "source": {
                "id": null,
                "name": "Biztoc.com"
            },
            "author": "barchart.com",
            "title": "Should You Buy the Dip in DocuSign After Earnings?",
            "description": "Your browser of choice has not been tested for use with Barchart.com. If you have issues, please download one of the browsers listed here.\nJoin Barchart Premier to get Screeners that run automatically with the results emailed to you!\nFREE 30 Day Trial\n- Marke\u2026",
            "url": "https://biztoc.com/x/d2269789137d7f44",
            "urlToImage": "https://biztoc.com/cdn/d2269789137d7f44_s.webp",
            "publishedAt": "2024-06-16T12:05:49Z",
            "content": "Your browser of choice has not been tested for use with Barchart.com. If you have issues, please download one of the browsers listed here.Join Barchart Premier to get Screeners that run automatically\u2026 [+128 chars]"
        },
        {
            "source": {
                "id": null,
                "name": "Biztoc.com"
            },
            "author": "seekingalpha.com",
            "title": "DocuSign: 33% FCF Margins, But Slowing Growth Is A Risk",
            "description": "DocuSign (NASDAQ:DOCU) reported better than expected first fiscal quarter results, which were released on June 6, 2024. The e-Signature leader reported slowing top-line growth, which was expected, and also revealed persistent risks to its dollar net retention\u2026",
            "url": "https://biztoc.com/x/83e6b89d45a01415",
            "urlToImage": "https://biztoc.com/cdn/83e6b89d45a01415_s.webp",
            "publishedAt": "2024-06-18T07:44:37Z",
            "content": "DocuSign (NASDAQ:DOCU) reported better than expected first fiscal quarter results, which were released on June 6, 2024. The e-Signature leader reported slowing top-line growth, which was expected, an\u2026 [+137 chars]"
        },
        {
            "source": {
                "id": null,
                "name": "ETF Daily News"
            },
            "author": "MarketBeat News",
            "title": "DocuSign, Inc. (NASDAQ:DOCU) Shares Purchased by Quarry LP",
            "description": "Quarry LP increased its holdings in DocuSign, Inc. (NASDAQ:DOCU \u2013 Free Report) by 177.9% in the 4th quarter, HoldingsChannel reports. The fund owned 1,209 shares of the company\u2019s stock after purchasing an additional 774 shares during the quarter. Quarry LP\u2019s \u2026",
            "url": "https://www.etfdailynews.com/2024/06/16/docusign-inc-nasdaqdocu-shares-purchased-by-quarry-lp/",
            "urlToImage": "https://www.americanbankingnews.com/wp-content/timthumb/timthumb.php?src=https://www.marketbeat.com/logos/docusign-inc-logo-1200x675.jpg?v=20240109092218&w=240&h=240&zc=2",
            "publishedAt": "2024-06-16T08:26:47Z",
            "content": "Quarry LP increased its holdings in DocuSign, Inc. (NASDAQ:DOCU \u2013 Free Report) by 177.9% in the 4th quarter, HoldingsChannel reports. The fund owned 1,209 shares of the company\u2019s stock after purchasi\u2026 [+5633 chars]"
        },
        {
            "source": {
                "id": null,
                "name": "Investing.com"
            },
            "author": "Investing.com",
            "title": "Docusign is focused on building a great, independent public company",
            "description": "DocuSign CEO wants to build 'a great, independent public company'",
            "url": "https://www.investing.com/news/stock-market-news/docusign-ceo-says-firm-wants-to-stay-public-after-reports-of-takeover-interest--cnbc-432SI-3452095",
            "urlToImage": "https://i-invdn-com.investing.com/news/LYNXMPEA7H0NX_L.jpg",
            "publishedAt": "2024-05-22T21:08:51Z",
            "content": "DocuSign (NASDAQ:DOCU) is committed to remaining a public, independent company and is working to convince investors of its artificial intelligence potential, the companys CEO Allan Thygesen told CNBC\u2026 [+1047 chars]"
        },
        {
            "source": {
                "id": null,
                "name": "Biztoc.com"
            },
            "author": "finance.yahoo.com",
            "title": "DocuSign stock down on lower-than-expected Q2 billings guidance",
            "description": "Yahoo Finance's Julie Hyman breaks down the biggest stocks moving in after-hours trading. Shares of DocuSign (DOCU) are falling after the company's second quarter billings guidance fell below Wall Street expectations. However, the company did beat earnings es\u2026",
            "url": "https://biztoc.com/x/bd9cb3d04c367b6c",
            "urlToImage": "https://c.biztoc.com/p/bd9cb3d04c367b6c/og.webp",
            "publishedAt": "2024-06-07T12:30:08Z",
            "content": "Yahoo Finance's Julie Hyman breaks down the biggest stocks moving in after-hours trading.Shares of DocuSign (DOCU) are falling after the company's second quarter billings guidance fell below Wall Str\u2026 [+291 chars]"
        },
        {
            "source": {
                "id": null,
                "name": "Marketscreener.com"
            },
            "author": null,
            "title": "Docusign : Q1 Fiscal 2025 Earnings Call and Webcast Prepared Remarks",
            "description": "(marketscreener.com) \n \n \n Q1 FY25 Investor Prepared Remarks\n \n \n June 6, 2024\n \n \n Allan Thygesen, CEO\n \n \n Blake Grayson, CFO\n \n \n \n \n \n \n \n Docusign Q1'25 Investor Prepared Remarks\n \n ...https://www.marketscreener.com/quote/stock/DOCUSIGN-INC-43180302/news\u2026",
            "url": "https://www.marketscreener.com/quote/stock/DOCUSIGN-INC-43180302/news/Docusign-Q1-Fiscal-2025-Earnings-Call-and-Webcast-Prepared-Remarks-46923843/",
            "urlToImage": "https://www.marketscreener.com/images/twitter_MS_fdblanc.png",
            "publishedAt": "2024-06-06T22:03:05Z",
            "content": "This presentation contains \"forward-looking\" statements within the meaning of Section 27A of the Securities Act of 1933, as amended, and Section 21E of the Securities Exchange Act of 1934, as amended\u2026 [+10401 chars]"
        },
        {
            "source": {
                "id": null,
                "name": "ETF Daily News"
            },
            "author": "MarketBeat News",
            "title": "Bank of America Lowers DocuSign (NASDAQ:DOCU) Price Target to $60.00",
            "description": "DocuSign (NASDAQ:DOCU \u2013 Free Report) had its price objective decreased by Bank of America from $72.00 to $60.00 in a report issued on Friday morning, Benzinga reports. Bank of America currently has a neutral rating on the stock. A number of other analysts als\u2026",
            "url": "https://www.etfdailynews.com/2024/06/08/bank-of-america-lowers-docusign-nasdaqdocu-price-target-to-60-00/",
            "urlToImage": "https://www.americanbankingnews.com/wp-content/timthumb/timthumb.php?src=https://www.marketbeat.com/logos/docusign-inc-logo.jpg?v=20240109092218&w=240&h=240&zc=2",
            "publishedAt": "2024-06-08T10:46:41Z",
            "content": "DocuSign (NASDAQ:DOCU \u2013 Free Report) had its price objective decreased by Bank of America from $72.00 to $60.00 in a report issued on Friday morning, Benzinga reports. Bank of America currently has a\u2026 [+5721 chars]"
        },
        {
            "source": {
                "id": null,
                "name": "ETF Daily News"
            },
            "author": "MarketBeat News",
            "title": "DocuSign (NASDAQ:DOCU) Given \u201cMarket Outperform\u201d Rating at JMP Securities",
            "description": "JMP Securities reiterated their market outperform rating on shares of DocuSign (NASDAQ:DOCU \u2013 Free Report) in a report published on Friday morning, Benzinga reports. JMP Securities currently has a $84.00 price target on the stock. Several other equities analy\u2026",
            "url": "https://www.etfdailynews.com/2024/06/08/docusign-nasdaqdocu-given-market-outperform-rating-at-jmp-securities/",
            "urlToImage": "https://www.americanbankingnews.com/wp-content/timthumb/timthumb.php?src=https://www.marketbeat.com/logos/docusign-inc-logo.jpg?v=20240109092218&w=240&h=240&zc=2",
            "publishedAt": "2024-06-08T10:46:41Z",
            "content": "JMP Securities reiterated their market outperform rating on shares of DocuSign (NASDAQ:DOCU \u2013 Free Report) in a report published on Friday morning, Benzinga reports. JMP Securities currently has a $8\u2026 [+5529 chars]"
        },
        {
            "source": {
                "id": null,
                "name": "ETF Daily News"
            },
            "author": "MarketBeat News",
            "title": "Commerce Bank Reduces Stock Position in DocuSign, Inc. (NASDAQ:DOCU)",
            "description": "Commerce Bank lowered its stake in shares of DocuSign, Inc. (NASDAQ:DOCU \u2013 Free Report) by 10.0% during the 4th quarter, according to the company in its most recent disclosure with the Securities and Exchange Commission (SEC). The institutional investor owned\u2026",
            "url": "https://www.etfdailynews.com/2024/05/31/commerce-bank-reduces-stock-position-in-docusign-inc-nasdaqdocu/",
            "urlToImage": "https://www.americanbankingnews.com/wp-content/timthumb/timthumb.php?src=https://www.marketbeat.com/logos/docusign-inc-logo-1200x675.jpg?v=20240109092218&w=240&h=240&zc=2",
            "publishedAt": "2024-05-31T10:22:44Z",
            "content": "Commerce Bank lowered its stake in shares of DocuSign, Inc. (NASDAQ:DOCU \u2013 Free Report) by 10.0% during the 4th quarter, according to the company in its most recent disclosure with the Securities and\u2026 [+6070 chars]"
        },
        {
            "source": {
                "id": null,
                "name": "ETF Daily News"
            },
            "author": "MarketBeat News",
            "title": "Dimensional Fund Advisors LP Grows Holdings in DocuSign, Inc. (NASDAQ:DOCU)",
            "description": "Dimensional Fund Advisors LP grew its stake in DocuSign, Inc. (NASDAQ:DOCU \u2013 Free Report) by 30.2% during the fourth quarter, Holdings Channel.com reports. The fund owned 450,229 shares of the company\u2019s stock after acquiring an additional 104,536 shares durin\u2026",
            "url": "https://www.etfdailynews.com/2024/06/03/dimensional-fund-advisors-lp-grows-holdings-in-docusign-inc-nasdaqdocu/",
            "urlToImage": "https://www.americanbankingnews.com/wp-content/timthumb/timthumb.php?src=https://www.marketbeat.com/logos/docusign-inc-logo-1200x675.jpg?v=20240109092218&w=240&h=240&zc=2",
            "publishedAt": "2024-06-03T09:02:52Z",
            "content": "Dimensional Fund Advisors LP grew its stake in DocuSign, Inc. (NASDAQ:DOCU \u2013 Free Report) by 30.2% during the fourth quarter, Holdings Channel.com reports. The fund owned 450,229 shares of the compan\u2026 [+6185 chars]"
        },
        {
            "source": {
                "id": null,
                "name": "Biztoc.com"
            },
            "author": "marketbeat.com",
            "title": "DocuSign: Can AI Move the Needle in Fiscal 2025?",
            "description": "DocuSign Inc. NASDAQ: DOCU provides electronic signature and contract lifecycle management (LCM) services. Shares hit highs of $314.70 in 2021 as business surged from the pandemic as businesses and individuals adopted remote meetings and contract signings. Sh\u2026",
            "url": "https://biztoc.com/x/97443ade679561a6",
            "urlToImage": "https://c.biztoc.com/274/og.png",
            "publishedAt": "2024-06-03T14:32:05Z",
            "content": "DocuSign Inc. NASDAQ: DOCU provides electronic signature and contract lifecycle management (LCM) services. Shares hit highs of $314.70 in 2021 as business surged from the pandemic as businesses and i\u2026 [+280 chars]"
        },
        {
            "source": {
                "id": null,
                "name": "ETF Daily News"
            },
            "author": "MarketBeat News",
            "title": "Advisory Services Network LLC Decreases Holdings in DocuSign, Inc. (NASDAQ:DOCU)",
            "description": "Advisory Services Network LLC reduced its position in shares of DocuSign, Inc. (NASDAQ:DOCU \u2013 Free Report) by 37.0% in the 4th quarter, according to the company in its most recent 13F filing with the Securities and Exchange Commission. The institutional inves\u2026",
            "url": "https://www.etfdailynews.com/2024/05/29/advisory-services-network-llc-decreases-holdings-in-docusign-inc-nasdaqdocu/",
            "urlToImage": "https://www.americanbankingnews.com/wp-content/timthumb/timthumb.php?src=https://www.marketbeat.com/logos/docusign-inc-logo-1200x675.jpg?v=20240109092218&w=240&h=240&zc=2",
            "publishedAt": "2024-05-29T12:04:49Z",
            "content": "Advisory Services Network LLC reduced its position in shares of DocuSign, Inc. (NASDAQ:DOCU \u2013 Free Report) by 37.0% in the 4th quarter, according to the company in its most recent 13F filing with the\u2026 [+5965 chars]"
        },
        {
            "source": {
                "id": null,
                "name": "ETF Daily News"
            },
            "author": "MarketBeat News",
            "title": "Prudential PLC Has $577,000 Position in DocuSign, Inc. (NASDAQ:DOCU)",
            "description": "Prudential PLC raised its stake in shares of DocuSign, Inc. (NASDAQ:DOCU \u2013 Free Report) by 55.7% in the 4th quarter, according to its most recent 13F filing with the Securities and Exchange Commission. The firm owned 9,702 shares of the company\u2019s stock after \u2026",
            "url": "https://www.etfdailynews.com/2024/06/12/prudential-plc-has-577000-position-in-docusign-inc-nasdaqdocu/",
            "urlToImage": "https://www.americanbankingnews.com/wp-content/timthumb/timthumb.php?src=https://www.marketbeat.com/logos/docusign-inc-logo-1200x675.jpg?v=20240109092218&w=240&h=240&zc=2",
            "publishedAt": "2024-06-12T08:16:45Z",
            "content": "Prudential PLC raised its stake in shares of DocuSign, Inc. (NASDAQ:DOCU \u2013 Free Report) by 55.7% in the 4th quarter, according to its most recent 13F filing with the Securities and Exchange Commissio\u2026 [+5309 chars]"
        },
        {
            "source": {
                "id": null,
                "name": "Biztoc.com"
            },
            "author": "benzinga.com",
            "title": "HealthLynked Introduces Innovative Online Medical Record Request Form Using DocuSign",
            "description": "NAPLES, Fla., June 12, 2024 (GLOBE NEWSWIRE) -- via IBN \u2013 HealthLynked Corp. HLYK, a leading provider of healthcare technology solutions, announces its new online medical record request form, integrated with DocuSign. With just a few clicks, this cutting-edge\u2026",
            "url": "https://biztoc.com/x/26e0881cf692d1c8",
            "urlToImage": "https://biztoc.com/cdn/26e0881cf692d1c8_s.webp",
            "publishedAt": "2024-06-12T12:16:13Z",
            "content": "NAPLES, Fla., June 12, 2024 (GLOBE NEWSWIRE) -- via IBN HealthLynked Corp. HLYK, a leading provider of healthcare technology solutions, announces its new online medical record request form, integrate\u2026 [+134 chars]"
        },
        {
            "source": {
                "id": null,
                "name": "ETF Daily News"
            },
            "author": "MarketBeat News",
            "title": "Rathbones Group PLC Grows Stake in DocuSign, Inc. (NASDAQ:DOCU)",
            "description": "Rathbones Group PLC increased its holdings in DocuSign, Inc. (NASDAQ:DOCU \u2013 Free Report) by 8.0% during the fourth quarter, HoldingsChannel reports. The institutional investor owned 38,867 shares of the company\u2019s stock after acquiring an additional 2,870 shar\u2026",
            "url": "https://www.etfdailynews.com/2024/06/04/rathbones-group-plc-grows-stake-in-docusign-inc-nasdaqdocu/",
            "urlToImage": "https://www.americanbankingnews.com/wp-content/timthumb/timthumb.php?src=https://www.marketbeat.com/logos/docusign-inc-logo-1200x675.jpg?v=20240109092218&w=240&h=240&zc=2",
            "publishedAt": "2024-06-04T12:22:42Z",
            "content": "Rathbones Group PLC increased its holdings in DocuSign, Inc. (NASDAQ:DOCU \u2013 Free Report) by 8.0% during the fourth quarter, HoldingsChannel reports. The institutional investor owned 38,867 shares of \u2026 [+6153 chars]"
        },
        {
            "source": {
                "id": null,
                "name": "Investing.com"
            },
            "author": "Investing.com",
            "title": "Docusign seeks sustainable growth post-pandemic; JPMorgan keeps stock underweight",
            "description": "Docusign seeks sustainable growth post-pandemic; JPMorgan keeps stock underweight",
            "url": "https://www.investing.com/news/company-news/docusign-seeks-sustainable-growth-postpandemic-jpmorgan-keeps-stock-underweight-93CH-3471446",
            "urlToImage": "https://i-invdn-com.investing.com/news/World_News_8_800x533_L_1420026210.jpg",
            "publishedAt": "2024-06-05T11:52:50Z",
            "content": "On Wednesday, JPMorgan maintained its Underweight rating on Docusign Inc. (NASDAQ: DOCU), with a steady price target of $50.00. Docusign, a leader in the contract-lifecycle management market, is know\u2026 [+2737 chars]"
        },
        {
            "source": {
                "id": null,
                "name": "Biztoc.com"
            },
            "author": "aol.com",
            "title": "DocuSign Shares Sink on Guidance. Time to Buy the Dip?",
            "description": "Shares of DocuSign (NASDAQ: DOCU) were sliding after the electronic signature-solutions provider reported its fiscal 2025 first-quarter results. The stock is down over 10% year to date after a late surge in 2023 when the company was close to selling itself to\u2026",
            "url": "https://biztoc.com/x/9b0a15110c3c2af9",
            "urlToImage": "https://c.biztoc.com/p/9b0a15110c3c2af9/s.webp",
            "publishedAt": "2024-06-09T19:18:04Z",
            "content": "Shares of DocuSign (NASDAQ: DOCU) were sliding after the electronic signature-solutions provider reported its fiscal 2025 first-quarter results. The stock is down over 10% year to date after a late s\u2026 [+267 chars]"
        },
        {
            "source": {
                "id": null,
                "name": "ETF Daily News"
            },
            "author": "MarketBeat News",
            "title": "MMTec (NASDAQ:MTC) and DocuSign (NASDAQ:DOCU) Head to Head Survey",
            "description": "MMTec (NASDAQ:MTC \u2013 Get Free Report) and DocuSign (NASDAQ:DOCU \u2013 Get Free Report) are both business services companies, but which is the superior investment? We will contrast the two companies based on the strength of their valuation, profitability, risk, ins\u2026",
            "url": "https://www.etfdailynews.com/2024/06/13/mmtec-nasdaqmtc-and-docusign-nasdaqdocu-head-to-head-survey/",
            "urlToImage": "https://www.americanbankingnews.com/wp-content/timthumb/timthumb.php?src=https://www.marketbeat.com/logos/docusign-inc-logo-1200x675.jpg?v=20240109092218&w=240&h=240&zc=2",
            "publishedAt": "2024-06-13T05:40:42Z",
            "content": "MMTec (NASDAQ:MTC \u2013 Get Free Report) and DocuSign (NASDAQ:DOCU \u2013 Get Free Report) are both business services companies, but which is the superior investment? We will contrast the two companies based \u2026 [+5432 chars]"
        },
        {
            "source": {
                "id": null,
                "name": "ETF Daily News"
            },
            "author": "MarketBeat News",
            "title": "Allianz Asset Management GmbH Buys 65,316 Shares of DocuSign, Inc. (NASDAQ:DOCU)",
            "description": "Allianz Asset Management GmbH grew its stake in DocuSign, Inc. (NASDAQ:DOCU \u2013 Free Report) by 32.2% during the fourth quarter, according to its most recent 13F filing with the Securities and Exchange Commission. The firm owned 268,395 shares of the company\u2019s \u2026",
            "url": "https://www.etfdailynews.com/2024/06/02/allianz-asset-management-gmbh-buys-65316-shares-of-docusign-inc-nasdaqdocu/",
            "urlToImage": "https://www.americanbankingnews.com/wp-content/timthumb/timthumb.php?src=https://www.marketbeat.com/logos/docusign-inc-logo-1200x675.jpg?v=20240109092218&w=240&h=240&zc=2",
            "publishedAt": "2024-06-02T13:04:48Z",
            "content": "Allianz Asset Management GmbH grew its stake in DocuSign, Inc. (NASDAQ:DOCU \u2013 Free Report) by 32.2% during the fourth quarter, according to its most recent 13F filing with the Securities and Exchange\u2026 [+6284 chars]"
        },
        {
            "source": {
                "id": null,
                "name": "Biztoc.com"
            },
            "author": "cnbc.com",
            "title": "DocuSign chief says company wants to stay public after reports of private equity takeover interest",
            "description": "The DocuSign website is seen on a laptop in Dobbs Ferry, New York, April 1, 2021. Contract management platform DocuSign is committed to remaining a public company and is working to convince investors of its artificial intelligence potential, CEO Allan Thygese\u2026",
            "url": "https://biztoc.com/x/5287ecfdd966da91",
            "urlToImage": "https://c.biztoc.com/p/5287ecfdd966da91/s.webp",
            "publishedAt": "2024-05-22T08:00:05Z",
            "content": "The DocuSign website is seen on a laptop in Dobbs Ferry, New York, April 1, 2021.Contract management platform DocuSign is committed to remaining a public company and is working to convince investors \u2026 [+280 chars]"
        },
        {
            "source": {
                "id": null,
                "name": "ETF Daily News"
            },
            "author": "MarketBeat News",
            "title": "Rafferty Asset Management LLC Acquires 3,431 Shares of DocuSign, Inc. (NASDAQ:DOCU)",
            "description": "Rafferty Asset Management LLC raised its holdings in shares of DocuSign, Inc. (NASDAQ:DOCU \u2013 Free Report) by 7.4% in the fourth quarter, HoldingsChannel reports. The firm owned 49,897 shares of the company\u2019s stock after buying an additional 3,431 shares durin\u2026",
            "url": "https://www.etfdailynews.com/2024/06/09/rafferty-asset-management-llc-acquires-3431-shares-of-docusign-inc-nasdaqdocu/",
            "urlToImage": "https://www.americanbankingnews.com/wp-content/timthumb/timthumb.php?src=https://www.marketbeat.com/logos/docusign-inc-logo-1200x675.jpg?v=20240109092218&w=240&h=240&zc=2",
            "publishedAt": "2024-06-09T09:44:42Z",
            "content": "Rafferty Asset Management LLC raised its holdings in shares of DocuSign, Inc. (NASDAQ:DOCU \u2013 Free Report) by 7.4% in the fourth quarter, HoldingsChannel reports. The firm owned 49,897 shares of the c\u2026 [+6138 chars]"
        },
        {
            "source": {
                "id": null,
                "name": "ETF Daily News"
            },
            "author": "MarketBeat News",
            "title": "DocuSign, Inc. (NASDAQ:DOCU) Insider James P. Shaughnessy Sells 1,800 Shares of Stock",
            "description": "DocuSign, Inc. (NASDAQ:DOCU \u2013 Get Free Report) insider James P. Shaughnessy sold 1,800 shares of the firm\u2019s stock in a transaction that occurred on Tuesday, June 11th. The shares were sold at an average price of $50.98, for a total transaction of $91,764.00. \u2026",
            "url": "https://www.etfdailynews.com/2024/06/13/docusign-inc-nasdaqdocu-insider-james-p-shaughnessy-sells-1800-shares-of-stock/",
            "urlToImage": "https://www.americanbankingnews.com/wp-content/timthumb/timthumb.php?src=https://www.marketbeat.com/logos/docusign-inc-logo-1200x675.jpg?v=20240109092218&w=240&h=240&zc=2",
            "publishedAt": "2024-06-13T13:16:43Z",
            "content": "DocuSign, Inc. (NASDAQ:DOCU \u2013 Get Free Report) insider James P. Shaughnessy sold 1,800 shares of the firm\u2019s stock in a transaction that occurred on Tuesday, June 11th. The shares were sold at an aver\u2026 [+3961 chars]"
        },
        {
            "source": {
                "id": null,
                "name": "ETF Daily News"
            },
            "author": "MarketBeat News",
            "title": "DocuSign, Inc. (NASDAQ:DOCU) Shares Sold by PNC Financial Services Group Inc.",
            "description": "PNC Financial Services Group Inc. cut its holdings in DocuSign, Inc. (NASDAQ:DOCU \u2013 Free Report) by 19.7% during the fourth quarter, according to the company in its most recent Form 13F filing with the Securities and Exchange Commission (SEC). The institution\u2026",
            "url": "https://www.etfdailynews.com/2024/06/06/docusign-inc-nasdaqdocu-shares-sold-by-pnc-financial-services-group-inc/",
            "urlToImage": "https://www.americanbankingnews.com/wp-content/timthumb/timthumb.php?src=https://www.marketbeat.com/logos/docusign-inc-logo-1200x675.jpg?v=20240109092218&w=240&h=240&zc=2",
            "publishedAt": "2024-06-06T09:50:45Z",
            "content": "PNC Financial Services Group Inc. cut its holdings in DocuSign, Inc. (NASDAQ:DOCU \u2013 Free Report) by 19.7% during the fourth quarter, according to the company in its most recent Form 13F filing with t\u2026 [+6140 chars]"
        },
        {
            "source": {
                "id": null,
                "name": "ETF Daily News"
            },
            "author": "MarketBeat News",
            "title": "DocuSign (NASDAQ:DOCU) Price Target Cut to $86.00 by Analysts at Citigroup",
            "description": "DocuSign (NASDAQ:DOCU \u2013 Free Report) had its target price trimmed by Citigroup from $93.00 to $86.00 in a report published on Wednesday, Benzinga reports. The firm currently has a buy rating on the stock. A number of other brokerages also recently commented o\u2026",
            "url": "https://www.etfdailynews.com/2024/06/06/docusign-nasdaqdocu-price-target-cut-to-86-00-by-analysts-at-citigroup/",
            "urlToImage": "https://www.americanbankingnews.com/wp-content/timthumb/timthumb.php?src=https://www.marketbeat.com/logos/docusign-inc-logo.jpg?v=20240109092218&w=240&h=240&zc=2",
            "publishedAt": "2024-06-06T08:22:42Z",
            "content": "DocuSign (NASDAQ:DOCU \u2013 Free Report) had its target price trimmed by Citigroup from $93.00 to $86.00 in a report published on Wednesday, Benzinga reports. The firm currently has a buy rating on the s\u2026 [+5621 chars]"
        },
        {
            "source": {
                "id": null,
                "name": "ETF Daily News"
            },
            "author": "MarketBeat News",
            "title": "Treasurer of the State of North Carolina Grows Holdings in DocuSign, Inc. (NASDAQ:DOCU)",
            "description": "Treasurer of the State of North Carolina raised its position in shares of DocuSign, Inc. (NASDAQ:DOCU \u2013 Free Report) by 1.0% during the 4th quarter, according to its most recent disclosure with the Securities and Exchange Commission (SEC). The institutional i\u2026",
            "url": "https://www.etfdailynews.com/2024/06/03/treasurer-of-the-state-of-north-carolina-grows-holdings-in-docusign-inc-nasdaqdocu/",
            "urlToImage": "https://www.americanbankingnews.com/wp-content/timthumb/timthumb.php?src=https://www.marketbeat.com/logos/docusign-inc-logo-1200x675.jpg?v=20240109092218&w=240&h=240&zc=2",
            "publishedAt": "2024-06-03T11:26:47Z",
            "content": "Treasurer of the State of North Carolina raised its position in shares of DocuSign, Inc. (NASDAQ:DOCU \u2013 Free Report) by 1.0% during the 4th quarter, according to its most recent disclosure with the S\u2026 [+6145 chars]"
        },
        {
            "source": {
                "id": null,
                "name": "Biztoc.com"
            },
            "author": "wsj.com",
            "title": "Docusign, After Riding Pandemic Wave, Aims to Expand Beyond E-Signature",
            "description": "The company is hoping to boost revenue by selling a new platform that uses artificial intelligence to help store and analyze contracts.",
            "url": "https://biztoc.com/x/8588e27ebe179d89",
            "urlToImage": "https://biztoc.com/cdn/799/og.png",
            "publishedAt": "2024-06-21T10:07:01Z",
            "content": "The company is hoping to boost revenue by selling a new platform that uses artificial intelligence to help store and analyze contracts.\r\nThis story appeared on wsj.com, 2024-06-21."
        },
        {
            "source": {
                "id": null,
                "name": "Biztoc.com"
            },
            "author": "benzinga.com",
            "title": "Kno2 and Docusign Revolutionize Provider-to-Provider Signature Workflows in Healthcare",
            "description": "BOISE, Idaho, May 23, 2024 (GLOBE NEWSWIRE) -- Kno2\u00ae, the leader in interoperable healthcare communication is excited to announce the transformation of provider-to-provider signature workflows in the healthcare industry with one of the world's leaders in e-si\u2026",
            "url": "https://biztoc.com/x/0f709a18d64e61be",
            "urlToImage": "https://c.biztoc.com/p/0f709a18d64e61be/s.webp",
            "publishedAt": "2024-05-23T15:16:07Z",
            "content": "BOISE, Idaho, May 23, 2024 (GLOBE NEWSWIRE) -- Kno2\u00ae, the leader in interoperable healthcare communication is excited to announce the transformation of provider-to-provider signature workflows in the\u2026 [+276 chars]"
        },
        {
            "source": {
                "id": null,
                "name": "GlobeNewswire"
            },
            "author": "Kno2",
            "title": "Kno2 and Docusign Revolutionize Provider-to-Provider Signature Workflows in Healthcare",
            "description": "Kno2 and Docusign partner to enhance signature process between referring providers ......",
            "url": "https://www.globenewswire.com/news-release/2024/05/23/2887445/0/en/Kno2-and-Docusign-Revolutionize-Provider-to-Provider-Signature-Workflows-in-Healthcare.html",
            "urlToImage": "https://ml.globenewswire.com/Resource/Download/1fa0de60-dc0d-4dc8-935b-43ce8c3a306b",
            "publishedAt": "2024-05-23T15:05:00Z",
            "content": "BOISE, Idaho, May 23, 2024 (GLOBE NEWSWIRE) -- Kno2\u00ae, the leader in interoperable healthcare communication is excited to announce the transformation of provider-to-provider signature workflows in the\u2026 [+4185 chars]"
        },
        {
            "source": {
                "id": null,
                "name": "Biztoc.com"
            },
            "author": "fortune.com",
            "title": "Docusign CEO says while it\u2019s true Americans work harder than Europeans, maybe Americans aren\u2019t happier",
            "description": "In a tech hub like San Francisco, it\u2019s increasingly rare to find a job that will still let you work from home the majority of the week. But at $12 billion company Docusign, that\u2019s still the case\u2014in fact, nobody\u2019s required to come into the office on a Friday. \u2026",
            "url": "https://biztoc.com/x/d568adf5afb0c6a1",
            "urlToImage": "https://c.biztoc.com/p/d568adf5afb0c6a1/s.webp",
            "publishedAt": "2024-06-08T09:08:05Z",
            "content": "In a tech hub like San Francisco, its increasingly rare to find a job that will still let you work from home the majority of the week. But at $12 billion company Docusign, thats still the casein fact\u2026 [+301 chars]"
        },
        {
            "source": {
                "id": null,
                "name": "Marketscreener.com"
            },
            "author": null,
            "title": "Docusign Introduces New Connector for SAP Ariba Solutions at SAP Sapphire",
            "description": "(marketscreener.com) \n\nSAN FRANCISCO, June 4, 2024 /PRNewswire/ -- Docusign , a global leader in Intelligent Agreement Management, today announced the upcoming launch of its new Docusign Connector for SAP Ariba solutions \u2013 a new offering that automates workfl\u2026",
            "url": "https://www.marketscreener.com/quote/stock/DOCUSIGN-INC-43180302/news/Docusign-Introduces-New-Connector-for-SAP-Ariba-Solutions-at-SAP-Sapphire-46900176/",
            "urlToImage": "https://www.marketscreener.com/images/twitter_MS_fdblanc.png",
            "publishedAt": "2024-06-04T13:01:29Z",
            "content": "SAN FRANCISCO, June 4, 2024 /PRNewswire/ -- Docusign (NASDAQ: DOCU), a global leader in Intelligent Agreement Management, today announced the upcoming launch of its new Docusign Connector for SAP Ari\u2026 [+4983 chars]"
        },
        {
            "source": {
                "id": null,
                "name": "Marketscreener.com"
            },
            "author": null,
            "title": "Docusign Announces First Quarter Fiscal 2025 Financial Results; Announces $1.0 Billion Increase to Share Repurchase Program",
            "description": "(marketscreener.com) \n\nSAN FRANCISCO, June 6, 2024 /PRNewswire/ -- Docusign, Inc. today announced results for its fiscal quarter ended April\u00a030, 2024. Prepared remarks and the news release with the financial results will be accessible on Docusign's website at\u2026",
            "url": "https://www.marketscreener.com/quote/stock/DOCUSIGN-INC-43180302/news/Docusign-Announces-First-Quarter-Fiscal-2025-Financial-Results-Announces-1-0-Billion-Increase-to-S-46923109/",
            "urlToImage": "https://www.marketscreener.com/images/twitter_MS_fdblanc.png",
            "publishedAt": "2024-06-06T20:06:10Z",
            "content": "SAN FRANCISCO, June 6, 2024 /PRNewswire/ -- Docusign, Inc. (NASDAQ: DOCU) today announced results for its fiscal quarter ended April\u00a030, 2024. Prepared remarks and the news release with the financial\u2026 [+43583 chars]"
        },
        {
            "source": {
                "id": null,
                "name": "Biztoc.com"
            },
            "author": "cnbc.com",
            "title": "Stocks making the biggest moves after hours: Vail Resorts, DocuSign, Samsara, Braze and more",
            "description": "Check out the companies making headlines in extended trading. Vail Resorts \u2014 The resort operator saw its stock fall more than 5% after posting fiscal third-quarter earnings of $9.54 per share on revenue of $1.28 billion. Those results missed analysts' expecta\u2026",
            "url": "https://biztoc.com/x/bf3653d3c802ff9f",
            "urlToImage": "https://c.biztoc.com/p/bf3653d3c802ff9f/og.webp",
            "publishedAt": "2024-06-06T21:20:10Z",
            "content": "Check out the companies making headlines in extended trading. Vail Resorts The resort operator saw its stock fall more than 5% after posting fiscal third-quarter earnings of $9.54 per share on revenu\u2026 [+235 chars]"
        },
        {
            "source": {
                "id": null,
                "name": "ETF Daily News"
            },
            "author": "MarketBeat News",
            "title": "Vinva Investment Management Ltd Makes New Investment in DocuSign, Inc. (NASDAQ:DOCU)",
            "description": "Vinva Investment Management Ltd bought a new stake in DocuSign, Inc. (NASDAQ:DOCU \u2013 Free Report) during the 4th quarter, according to the company in its most recent 13F filing with the SEC. The fund bought 8,709 shares of the company\u2019s stock, valued at approx\u2026",
            "url": "https://www.etfdailynews.com/2024/06/09/vinva-investment-management-ltd-makes-new-investment-in-docusign-inc-nasdaqdocu/",
            "urlToImage": "https://www.americanbankingnews.com/wp-content/timthumb/timthumb.php?src=https://www.marketbeat.com/logos/docusign-inc-logo-1200x675.jpg?v=20240109092218&w=240&h=240&zc=2",
            "publishedAt": "2024-06-09T12:36:44Z",
            "content": "Vinva Investment Management Ltd bought a new stake in DocuSign, Inc. (NASDAQ:DOCU \u2013 Free Report) during the 4th quarter, according to the company in its most recent 13F filing with the SEC. The fund \u2026 [+5781 chars]"
        },
        {
            "source": {
                "id": null,
                "name": "ETF Daily News"
            },
            "author": "MarketBeat News",
            "title": "DocuSign, Inc. (NASDAQ:DOCU) Shares Acquired by Royal London Asset Management Ltd.",
            "description": "Royal London Asset Management Ltd. increased its stake in shares of DocuSign, Inc. (NASDAQ:DOCU \u2013 Free Report) by 6.4% in the 4th quarter, according to the company in its most recent disclosure with the Securities and Exchange Commission (SEC). The firm owned\u2026",
            "url": "https://www.etfdailynews.com/2024/06/09/docusign-inc-nasdaqdocu-shares-acquired-by-royal-london-asset-management-ltd/",
            "urlToImage": "https://www.americanbankingnews.com/wp-content/timthumb/timthumb.php?src=https://www.marketbeat.com/logos/docusign-inc-logo-1200x675.jpg?v=20240109092218&w=240&h=240&zc=2",
            "publishedAt": "2024-06-09T10:56:41Z",
            "content": "Royal London Asset Management Ltd. increased its stake in shares of DocuSign, Inc. (NASDAQ:DOCU \u2013 Free Report) by 6.4% in the 4th quarter, according to the company in its most recent disclosure with \u2026 [+6021 chars]"
        },
        {
            "source": {
                "id": null,
                "name": "ETF Daily News"
            },
            "author": "MarketBeat News",
            "title": "Royal Bank of Canada Lowers DocuSign (NASDAQ:DOCU) Price Target to $52.00",
            "description": "DocuSign (NASDAQ:DOCU \u2013 Get Free Report) had its price objective cut by stock analysts at Royal Bank of Canada from $59.00 to $52.00 in a report released on Friday, Benzinga reports. The brokerage presently has a \u201csector perform\u201d rating on the stock. Royal Ba\u2026",
            "url": "https://www.etfdailynews.com/2024/06/09/royal-bank-of-canada-lowers-docusign-nasdaqdocu-price-target-to-52-00/",
            "urlToImage": "https://www.americanbankingnews.com/wp-content/timthumb/timthumb.php?src=https://www.marketbeat.com/logos/docusign-inc-logo-1200x675.jpg?v=20240109092218&w=240&h=240&zc=2",
            "publishedAt": "2024-06-09T10:24:41Z",
            "content": "DocuSign (NASDAQ:DOCU \u2013 Get Free Report) had its price objective cut by stock analysts at Royal Bank of Canada from $59.00 to $52.00 in a report released on Friday, Benzinga reports. The brokerage pr\u2026 [+5748 chars]"
        },
        {
            "source": {
                "id": null,
                "name": "ETF Daily News"
            },
            "author": "MarketBeat News",
            "title": "Strategic Global Advisors LLC Invests $1.29 Million in DocuSign, Inc. (NASDAQ:DOCU)",
            "description": "Strategic Global Advisors LLC acquired a new position in shares of DocuSign, Inc. (NASDAQ:DOCU \u2013 Free Report) during the 4th quarter, Holdings Channel reports. The fund acquired 21,762 shares of the company\u2019s stock, valued at approximately $1,294,000. Several\u2026",
            "url": "https://www.etfdailynews.com/2024/06/11/strategic-global-advisors-llc-invests-1-29-million-in-docusign-inc-nasdaqdocu/",
            "urlToImage": "https://www.americanbankingnews.com/wp-content/timthumb/timthumb.php?src=https://www.marketbeat.com/logos/docusign-inc-logo-1200x675.jpg?v=20240109092218&w=240&h=240&zc=2",
            "publishedAt": "2024-06-11T12:56:55Z",
            "content": "Strategic Global Advisors LLC acquired a new position in shares of DocuSign, Inc. (NASDAQ:DOCU \u2013 Free Report) during the 4th quarter, Holdings Channel reports. The fund acquired 21,762 shares of the \u2026 [+5363 chars]"
        },
        {
            "source": {
                "id": null,
                "name": "ETF Daily News"
            },
            "author": "MarketBeat News",
            "title": "Healthcare of Ontario Pension Plan Trust Fund Makes New Investment in DocuSign, Inc. (NASDAQ:DOCU)",
            "description": "Healthcare of Ontario Pension Plan Trust Fund acquired a new position in shares of DocuSign, Inc. (NASDAQ:DOCU \u2013 Free Report) during the 4th quarter, according to its most recent Form 13F filing with the Securities & Exchange Commission. The fund acquired 70,\u2026",
            "url": "https://www.etfdailynews.com/2024/06/19/healthcare-of-ontario-pension-plan-trust-fund-makes-new-investment-in-docusign-inc-nasdaqdocu/",
            "urlToImage": "https://www.americanbankingnews.com/wp-content/timthumb/timthumb.php?src=https://www.marketbeat.com/logos/docusign-inc-logo-1200x675.jpg?v=20240109092218&w=240&h=240&zc=2",
            "publishedAt": "2024-06-19T09:44:49Z",
            "content": "Healthcare of Ontario Pension Plan Trust Fund acquired a new position in shares of DocuSign, Inc. (NASDAQ:DOCU \u2013 Free Report) during the 4th quarter, according to its most recent Form 13F filing with\u2026 [+5414 chars]"
        },
        {
            "source": {
                "id": null,
                "name": "ETF Daily News"
            },
            "author": "MarketBeat News",
            "title": "Public Employees Retirement Association of Colorado Sells 9,800 Shares of DocuSign, Inc. (NASDAQ:DOCU)",
            "description": "Public Employees Retirement Association of Colorado cut its position in shares of DocuSign, Inc. (NASDAQ:DOCU \u2013 Free Report) by 29.9% in the fourth quarter, according to the company in its most recent filing with the Securities & Exchange Commission. The inst\u2026",
            "url": "https://www.etfdailynews.com/2024/06/11/public-employees-retirement-association-of-colorado-sells-9800-shares-of-docusign-inc-nasdaqdocu/",
            "urlToImage": "https://www.americanbankingnews.com/wp-content/timthumb/timthumb.php?src=https://www.marketbeat.com/logos/docusign-inc-logo-1200x675.jpg?v=20240109092218&w=240&h=240&zc=2",
            "publishedAt": "2024-06-11T09:34:47Z",
            "content": "Public Employees Retirement Association of Colorado cut its position in shares of DocuSign, Inc. (NASDAQ:DOCU \u2013 Free Report) by 29.9% in the fourth quarter, according to the company in its most recen\u2026 [+5878 chars]"
        },
        {
            "source": {
                "id": null,
                "name": "Thefly.com"
            },
            "author": null,
            "title": "DocuSign price target lowered by $3 at Morgan Stanley, here's why",
            "description": "See the rest of the story here.\n\nthefly.com provides the latest financial news as it breaks. Known as a leader in market intelligence, The Fly's real-time, streaming news feed keeps individual investors, professional money managers, active traders, and corpor\u2026",
            "url": "https://thefly.com/permalinks/entry.php/id3930571/DOCU-DocuSign-price-target-lowered-by--at-Morgan-Stanley-heres-why",
            "urlToImage": "https://thefly.com/images/meta/streetresearch_recommendations.jpg",
            "publishedAt": "2024-06-07T10:47:15Z",
            "content": "Earnings calls, analyst events, roadshows and more"
        },
        {
            "source": {
                "id": null,
                "name": "ETF Daily News"
            },
            "author": "MarketBeat News",
            "title": "DocuSign (NASDAQ:DOCU) Given New $55.00 Price Target at Robert W. Baird",
            "description": "DocuSign (NASDAQ:DOCU \u2013 Free Report) had its target price cut by Robert W. Baird from $65.00 to $55.00 in a research note published on Friday morning, Benzinga reports. They currently have a neutral rating on the stock. DOCU has been the topic of several othe\u2026",
            "url": "https://www.etfdailynews.com/2024/06/08/docusign-nasdaqdocu-given-new-55-00-price-target-at-robert-w-baird/",
            "urlToImage": "https://www.americanbankingnews.com/wp-content/timthumb/timthumb.php?src=https://www.marketbeat.com/logos/docusign-inc-logo.jpg?v=20240109092218&w=240&h=240&zc=2",
            "publishedAt": "2024-06-08T10:46:43Z",
            "content": "DocuSign (NASDAQ:DOCU \u2013 Free Report) had its target price cut by Robert W. Baird from $65.00 to $55.00 in a research note published on Friday morning, Benzinga reports. They currently have a neutral \u2026 [+5515 chars]"
        },
        {
            "source": {
                "id": null,
                "name": "Biztoc.com"
            },
            "author": "marketwatch.com",
            "title": "DocuSign says business is stabilizing, but stock falls despite earnings beat",
            "description": "Despite upside in DocuSign Inc.\u2019s latest quarterly results, the electronic-signature software company\u2019s stock was falling in Thursday\u2019s extended trading. #docusignincs",
            "url": "https://biztoc.com/x/b4c9458d3a94e0b1",
            "urlToImage": "https://c.biztoc.com/274/og.png",
            "publishedAt": "2024-06-06T21:56:05Z",
            "content": "Despite upside in DocuSign Inc.s latest quarterly results, the electronic-signature software companys stock was falling in Thursdays extended trading.\r\n#docusignincs\r\nThis story appeared on marketwat\u2026 [+18 chars]"
        },
        {
            "source": {
                "id": null,
                "name": "Biztoc.com"
            },
            "author": "investorplace.com",
            "title": "DOCU Stock Earnings: DocuSign Beats EPS, Beats Revenue for Q1 2025",
            "description": "DocuSign (NASDAQ: ) just reported results for the first quarter of 2025. InvestorPlace Earnings is a project that leverages data from TradeSmith to automate coverage of quarterly earnings reports. InvestorPlace Earnings distills key takeaways including earnin\u2026",
            "url": "https://biztoc.com/x/28e331a14559e1ad",
            "urlToImage": "https://c.biztoc.com/p/28e331a14559e1ad/s.webp",
            "publishedAt": "2024-06-07T02:32:12Z",
            "content": "DocuSign (NASDAQ: ) just reported results for the first quarter of 2025.InvestorPlace Earnings is a project that leverages data from TradeSmith to automate coverage of quarterly earnings reports. Inv\u2026 [+222 chars]"
        },
        {
            "source": {
                "id": null,
                "name": "Biztoc.com"
            },
            "author": "newsweek.com",
            "title": "Docusign Delivers Trust, Security While Maintaining 'Ease of Use,' CEO Says",
            "description": "Over the past 20 years, Docusign has continued to modernize the agreement space while maintaining customer trust.",
            "url": "https://biztoc.com/x/251e9465b5e37451",
            "urlToImage": "https://biztoc.com/cdn/799/og.png",
            "publishedAt": "2024-06-12T13:54:57Z",
            "content": "Over the past 20 years, Docusign has continued to modernize the agreement space while maintaining customer trust.\r\nThis story appeared on newsweek.com, 2024-06-12."
        },
        {
            "source": {
                "id": null,
                "name": "ETF Daily News"
            },
            "author": "MarketBeat News",
            "title": "Campbell & CO Investment Adviser LLC Has $1.18 Million Holdings in DocuSign, Inc. (NASDAQ:DOCU)",
            "description": "Campbell & CO Investment Adviser LLC lifted its stake in shares of DocuSign, Inc. (NASDAQ:DOCU \u2013 Free Report) by 17.6% during the fourth quarter, according to its most recent disclosure with the Securities and Exchange Commission. The institutional investor o\u2026",
            "url": "https://www.etfdailynews.com/2024/06/05/campbell-co-investment-adviser-llc-has-1-18-million-holdings-in-docusign-inc-nasdaqdocu/",
            "urlToImage": "https://www.americanbankingnews.com/wp-content/timthumb/timthumb.php?src=https://www.marketbeat.com/logos/docusign-inc-logo-1200x675.jpg?v=20240109092218&w=240&h=240&zc=2",
            "publishedAt": "2024-06-05T11:38:51Z",
            "content": "Campbell &amp; CO Investment Adviser LLC lifted its stake in shares of DocuSign, Inc. (NASDAQ:DOCU \u2013 Free Report) by 17.6% during the fourth quarter, according to its most recent disclosure with the \u2026 [+6112 chars]"
        },
        {
            "source": {
                "id": null,
                "name": "ETF Daily News"
            },
            "author": "MarketBeat News",
            "title": "TD Asset Management Inc Has $1.04 Million Holdings in DocuSign, Inc. (NASDAQ:DOCU)",
            "description": "TD Asset Management Inc lowered its stake in DocuSign, Inc. (NASDAQ:DOCU \u2013 Free Report) by 35.7% during the fourth quarter, according to its most recent Form 13F filing with the Securities and Exchange Commission (SEC). The institutional investor owned 17,463\u2026",
            "url": "https://www.etfdailynews.com/2024/06/10/td-asset-management-inc-has-1-04-million-holdings-in-docusign-inc-nasdaqdocu/",
            "urlToImage": "https://www.americanbankingnews.com/wp-content/timthumb/timthumb.php?src=https://www.marketbeat.com/logos/docusign-inc-logo-1200x675.jpg?v=20240109092218&w=240&h=240&zc=2",
            "publishedAt": "2024-06-10T08:38:45Z",
            "content": "TD Asset Management Inc lowered its stake in DocuSign, Inc. (NASDAQ:DOCU \u2013 Free Report) by 35.7% during the fourth quarter, according to its most recent Form 13F filing with the Securities and Exchan\u2026 [+5810 chars]"
        },
        {
            "source": {
                "id": null,
                "name": "Biztoc.com"
            },
            "author": "aol.com",
            "title": "Docusign CEO says while it\u2019s objectively true that Americans work harder than Europeans, maybe Americans aren\u2019t necessarily happier",
            "description": "In a tech hub like San Francisco, it's increasingly rare to find a job that will still let you work from home the majority of the week. But at $12 billion company Docusign, that's still the case\u2014in fact, nobody's required to come into the office on a Friday. \u2026",
            "url": "https://biztoc.com/x/c6b9e9eb6d6ed0bb",
            "urlToImage": "https://c.biztoc.com/p/c6b9e9eb6d6ed0bb/s.webp",
            "publishedAt": "2024-06-08T11:18:05Z",
            "content": "In a tech hub like San Francisco, it's increasingly rare to find a job that will still let you work from home the majority of the week. But at $12 billion company Docusign, that's still the casein fa\u2026 [+299 chars]"
        },
        {
            "source": {
                "id": null,
                "name": "Investopedia"
            },
            "author": "Bill McColl",
            "title": "Docusign Revenue, Future Billings Raise Concerns, and Stock Drops",
            "description": "Docusign's first-quarter revenue only slightly beat analysts' forecasts, and its bookings guidance raised concerns about future growth.",
            "url": "https://www.investopedia.com/docusign-revenue-future-billings-raise-concerns-and-stock-drops-8660015",
            "urlToImage": "https://www.investopedia.com/thmb/DTAcMOZUgBGEsM1Wz_S3h2chvx8=/1500x0/filters:no_upscale():max_bytes(150000):strip_icc()/3784907-66188e8f22258-9463913cab4541f294023e515cbf515e.jpg",
            "publishedAt": "2024-06-07T15:12:01Z",
            "content": "<ul><li>Docusign's first-quarter revenue only slightly beat analysts' forecasts, and its billings guidance raised concerns about future growth.</li><li>The document-signing software provider's revenu\u2026 [+1532 chars]"
        }
    ]
}